lazy_fisher_yates_shuffler/__init__.py
lazy_fisher_yates_shuffler/bit_manager.py
lazy_fisher_yates_shuffler/persistence.py
lazy_fisher_yates_shuffler/shuffler.py
lazy_fisher_yates_shuffler-1.0.4.dist-info/METADATA
lazy_fisher_yates_shuffler-1.0.4.dist-info/WHEEL
lazy_fisher_yates_shuffler-1.0.4.dist-info/licenses/LICENSE
lazy_fisher_yates_shuffler-1.0.4.dist-info/RECORD
