Metadata-Version: 2.4
Name: lazy-fisher-yates-shuffler
Version: 1.0.4
Summary: Lazy Fisher-Yates shuffler
License: Apache-2.0
License-File: LICENSE
Author: Kevin Dean
Author-email: Kevin.Dean@datadevelopment.com
Requires-Python: >=3.9,<4.0
Classifier: License :: OSI Approved :: Apache Software License
Classifier: Programming Language :: Python :: 3
Classifier: Programming Language :: Python :: 3.9
Classifier: Programming Language :: Python :: 3.10
Classifier: Programming Language :: Python :: 3.11
Classifier: Programming Language :: Python :: 3.12
Classifier: Programming Language :: Python :: 3.13
Classifier: Programming Language :: Python :: 3.14
Requires-Dist: poetry-core (>=2.2.1,<3.0.0)
Project-URL: Repository, https://github.com/KDean-Dolphin/Python-Shuffler
